enk/__init__.py
enk/console.py
enk/filegen.py
enk/process.py
enk-0.3.dist-info/WHEEL
enk-0.3.dist-info/METADATA
enk-0.3.dist-info/RECORD
